{
  "120363421837797061@g.us": {
    "2026-01-08": {
      "6283854859219@s.whatsapp.net": {
        "nama": "𝙆𝙖𝙚𝙡",
        "time": "23.38"
      }
    }
  },
  "120363404660759443@g.us": {
    "2026-01-08": {
      "6283854859219@s.whatsapp.net": {
        "nama": "𝙆𝙖𝙚𝙡",
        "time": "23.40"
      }
    },
    "2026-01-09": {
      "6283119324196@s.whatsapp.net": {
        "nama": "anak baik masak ayam",
        "time": "06.07"
      }
    },
    "2026-01-16": {
      "6281938977351@s.whatsapp.net": {
        "nama": "EL Zeyraa",
        "time": "22.45"
      }
    },
    "2026-01-18": {
      "6283139638165@s.whatsapp.net": {
        "nama": "stazz^_•",
        "time": "23.37"
      }
    }
  },
  "120363427279917369@g.us": {
    "2026-01-09": {
      "6282254452388@s.whatsapp.net": {
        "nama": "Langg",
        "time": "05.41"
      },
      "6285640725979@s.whatsapp.net": {
        "nama": "—𝑿𝒄𝒚'𝑺",
        "time": "05.46"
      },
      "6285133831959@s.whatsapp.net": {
        "nama": "𝐀𝐩𝐨𝐲𝐲",
        "time": "07.00"
      }
    },
    "2026-01-10": {
      "6285133831959@s.whatsapp.net": {
        "nama": "a for apoy",
        "time": "12.21"
      },
      "6285377268778@s.whatsapp.net": {
        "nama": "Putrzz || Shiroko",
        "time": "12.22"
      }
    },
    "2026-01-16": {
      "6282254452388@s.whatsapp.net": {
        "nama": "Langg",
        "time": "16.54"
      },
      "6283827619899@s.whatsapp.net": {
        "nama": "Junnn",
        "time": "16.55"
      },
      "6285133831959@s.whatsapp.net": {
        "nama": "a for apoy",
        "time": "16.55"
      },
      "6283177617653@s.whatsapp.net": {
        "nama": "Ndraa",
        "time": "17.22"
      },
      "6285377268778@s.whatsapp.net": {
        "nama": "Putrzz || Shiroko",
        "time": "17.26"
      },
      "6281573182225@s.whatsapp.net": {
        "nama": "~Zarzx",
        "time": "17.32"
      }
    },
    "2026-01-17": {
      "6285133831959@s.whatsapp.net": {
        "nama": "a for apoy",
        "time": "04.41"
      },
      "6285377268778@s.whatsapp.net": {
        "nama": "Putrzz || Shiroko",
        "time": "04.41"
      },
      "62882007707283@s.whatsapp.net": {
        "nama": "raaa",
        "time": "07.22"
      },
      "601137440036@s.whatsapp.net": {
        "nama": "ryuuu is more tired🫩",
        "time": "07.28"
      },
      "62895619151722@s.whatsapp.net": {
        "nama": "𝕨ልʀ𝖙ᴇ𝕩",
        "time": "07.29"
      },
      "6288246847684@s.whatsapp.net": {
        "nama": "𝘼𝙩𝙤𝙢𝙞𝙘",
        "time": "07.30"
      },
      "6282225262133@s.whatsapp.net": {
        "nama": "Kaizo~(¬_¬)ﾉ",
        "time": "09.57"
      },
      "6285760164107@s.whatsapp.net": {
        "nama": "ramdan",
        "time": "10.01"
      },
      "6283827619899@s.whatsapp.net": {
        "nama": "Junnn",
        "time": "10.04"
      },
      "6283177617653@s.whatsapp.net": {
        "nama": "Ndraa",
        "time": "11.57"
      },
      "6281573182225@s.whatsapp.net": {
        "nama": "~Zarzx",
        "time": "12.36"
      }
    },
    "2026-01-18": {
      "6283177617653@s.whatsapp.net": {
        "nama": "Ndraa",
        "time": "02.57"
      },
      "601137440036@s.whatsapp.net": {
        "nama": "ryuuu is more tired🫩",
        "time": "06.39"
      },
      "62882007707283@s.whatsapp.net": {
        "nama": "raaa",
        "time": "07.48"
      },
      "6288246847684@s.whatsapp.net": {
        "nama": "𝘼𝙩𝙤𝙢𝙞𝙘",
        "time": "07.50"
      },
      "6281573182225@s.whatsapp.net": {
        "nama": "~Zarzx",
        "time": "07.58"
      },
      "6288213779282@s.whatsapp.net": {
        "nama": "fiz",
        "time": "08.00"
      },
      "6282225262133@s.whatsapp.net": {
        "nama": "Kaizo~(¬_¬)ﾉ",
        "time": "08.03"
      },
      "6283827619899@s.whatsapp.net": {
        "nama": "Junnn",
        "time": "12.01"
      },
      "6285377268778@s.whatsapp.net": {
        "nama": "Putrzz || Shiroko",
        "time": "15.54"
      }
    },
    "2026-01-19": {
      "6283177617653@s.whatsapp.net": {
        "nama": "Ndraa",
        "time": "15.13"
      }
    },
    "2026-01-20": {
      "6283827619899@s.whatsapp.net": {
        "nama": "Junnn",
        "time": "00.34"
      },
      "62895619151722@s.whatsapp.net": {
        "nama": "𝕨ልʀ𝖙ᴇ𝕩",
        "time": "00.35"
      },
      "6283171072466@s.whatsapp.net": {
        "nama": "Xenon",
        "time": "00.47"
      },
      "6288213779282@s.whatsapp.net": {
        "nama": "fiz",
        "time": "00.47"
      },
      "6283177617653@s.whatsapp.net": {
        "nama": "Ndraa",
        "time": "01.51"
      }
    }
  },
  "120363403016443146@g.us": {
    "2026-01-09": {
      "62895326332109@s.whatsapp.net": {
        "nama": "sianna",
        "time": "23.45"
      },
      "6285264358624@s.whatsapp.net": {
        "nama": "Araa ˃ 𖥦 ˂",
        "time": "23.45"
      }
    }
  }
}